celery_loaders/__init__.py
celery_loaders/celery_worker.py
celery_loaders/log/__init__.py
celery_loaders/log/setup_logging.py
celery_loaders/work_tasks/__init__.py
celery_loaders/work_tasks/always_fails_tasks.py
celery_loaders/work_tasks/celery_config.py
celery_loaders/work_tasks/custom_task.py
celery_loaders/work_tasks/get_celery_app.py
celery_loaders/work_tasks/tasks.py
celery_loaders-1.0.8.data/scripts/run-celery-task.py
celery_loaders-1.0.8.dist-info/LICENSE
celery_loaders-1.0.8.dist-info/METADATA
celery_loaders-1.0.8.dist-info/WHEEL
celery_loaders-1.0.8.dist-info/top_level.txt
celery_loaders-1.0.8.dist-info/RECORD
