Metadata-Version: 2.1
Name: celery-loaders
Version: 1.0.8
Summary: Celery Application and Task Loader Examples
Home-page: https://github.com/jay-johnson/celery-loaders
Author: Jay Johnson
Author-email: jay.p.h.johnson@gmail.com
License: UNKNOWN
Platform: UNKNOWN
Classifier: Development Status :: 5 - Production/Stable
Classifier: Intended Audience :: Developers
Classifier: License :: OSI Approved :: Apache Software License
Classifier: Operating System :: OS Independent
Classifier: Programming Language :: Python :: 2
Classifier: Programming Language :: Python :: 2.7
Classifier: Programming Language :: Python :: 3.5
Classifier: Programming Language :: Python :: 3.6
Classifier: Programming Language :: Python :: Implementation :: PyPy
Classifier: Topic :: Software Development :: Libraries :: Python Modules
Requires-Dist: celery (>=4.1.0)
Requires-Dist: colorlog
Requires-Dist: coverage
Requires-Dist: flake8 (>=3.4.1)
Requires-Dist: future
Requires-Dist: kombu (>=4.1.0)
Requires-Dist: mock
Requires-Dist: pep8 (>=1.7.1)
Requires-Dist: pylint
Requires-Dist: redis
Requires-Dist: spylunking
Requires-Dist: unittest2
